mongodb_migrations/__init__.py
mongodb_migrations/base.py
mongodb_migrations/cli.py
mongodb_migrations/config.py
mongodb_migrations-1.3.1.dist-info/LICENSE
mongodb_migrations-1.3.1.dist-info/METADATA
mongodb_migrations-1.3.1.dist-info/WHEEL
mongodb_migrations-1.3.1.dist-info/entry_points.txt
mongodb_migrations-1.3.1.dist-info/top_level.txt
mongodb_migrations-1.3.1.dist-info/RECORD
